{
    "Ar36": {
        "error": 0.0005207113414658342,
        "error_type": "SEM",
        "filter_outliers_dict": {
            "filter_outliers": true,
            "iterations": 1,
            "std_devs": 3,
            "use_iqr_filtering": false,
            "use_standard_deviation_filtering": false
        },
        "fit": "parabolic",
        "fn": 280,
        "include_baseline_error": true,
        "n": 280,
        "outlier_excluded": [],
        "reviewed": true,
        "user_excluded": [],
        "value": 0.026076769562991754
    },
    "Ar37": {
        "error": 0.004086541720949515,
        "error_type": "SEM",
        "filter_outliers_dict": {
            "filter_outliers": true,
            "iterations": 1,
            "std_devs": 3,
            "use_iqr_filtering": false,
            "use_standard_deviation_filtering": false
        },
        "fit": "linear",
        "fn": 280,
        "include_baseline_error": true,
        "n": 280,
        "outlier_excluded": [],
        "reviewed": true,
        "user_excluded": [],
        "value": 0.013098209658438078
    },
    "Ar38": {
        "error": 0.003334290558929738,
        "error_type": "SEM",
        "filter_outliers_dict": {
            "filter_outliers": true,
            "iterations": 1,
            "std_devs": 3,
            "use_iqr_filtering": false,
            "use_standard_deviation_filtering": false
        },
        "fit": "linear",
        "fn": 279,
        "include_baseline_error": true,
        "n": 280,
        "outlier_excluded": [
            41
        ],
        "reviewed": true,
        "user_excluded": [],
        "value": 0.1755565181864184
    },
    "Ar39": {
        "error": 0.019007688748493925,
        "error_type": "SEM",
        "filter_outliers_dict": {
            "filter_outliers": true,
            "iterations": 1,
            "std_devs": 3,
            "use_iqr_filtering": false,
            "use_standard_deviation_filtering": false
        },
        "fit": "parabolic",
        "fn": 278,
        "include_baseline_error": true,
        "n": 280,
        "outlier_excluded": [
            0,
            7
        ],
        "reviewed": true,
        "user_excluded": [],
        "value": 7.803063552367057
    },
    "Ar40": {
        "error": 0.12309005391216635,
        "error_type": "SEM",
        "filter_outliers_dict": {
            "filter_outliers": true,
            "iterations": 1,
            "std_devs": 3,
            "use_iqr_filtering": false,
            "use_standard_deviation_filtering": false
        },
        "fit": "parabolic",
        "fn": 278,
        "include_baseline_error": true,
        "n": 280,
        "outlier_excluded": [
            0,
            1
        ],
        "reviewed": true,
        "user_excluded": [],
        "value": 21.16001384018412
    },
    "Ar41": {
        "error": 0.016866950885226096,
        "error_type": "SEM",
        "filter_outliers_dict": {
            "filter_outliers": true,
            "iterations": 1,
            "std_devs": 3
        },
        "fit": "average",
        "value": -0.25581577442972475
    }
}