{
    "Ar36": {
        "error": 0.00017242287921923755,
        "error_type": "SEM",
        "filter_outliers_dict": {
            "filter_outliers": true,
            "iterations": 1,
            "std_devs": 2
        },
        "fit": "linear",
        "value": 0.015211101070596596
    },
    "Ar37": {
        "error": 0.002843261684986929,
        "error_type": "SEM",
        "filter_outliers_dict": {
            "filter_outliers": true,
            "iterations": 1,
            "std_devs": 2
        },
        "fit": "linear",
        "value": -0.015899980890541465
    },
    "Ar38": {
        "error": 0.0024462902335287413,
        "error_type": "SEM",
        "filter_outliers_dict": {
            "filter_outliers": true,
            "iterations": 1,
            "std_devs": 2
        },
        "fit": "linear",
        "value": 0.0702103283852029
    },
    "Ar39": {
        "error": 0.009457493038857963,
        "error_type": "SEM",
        "filter_outliers_dict": {
            "filter_outliers": true,
            "iterations": 1,
            "std_devs": 2
        },
        "fit": "parabolic",
        "value": 0.5968153047755926
    },
    "Ar40": {
        "error": 0.009464736431207878,
        "error_type": "SEM",
        "filter_outliers_dict": {
            "filter_outliers": true,
            "iterations": 1,
            "std_devs": 3
        },
        "fit": "parabolic",
        "value": 4.7311579781482225
    },
    "Ar41": {
        "error": 0.015081819512414692,
        "error_type": "SEM",
        "filter_outliers_dict": {
            "filter_outliers": true,
            "iterations": 1,
            "std_devs": 3
        },
        "fit": "average",
        "value": -0.18793397727020933
    }
}