{
    "Ar36": {
        "error": 0.0001895597685164948,
        "error_type": "SEM",
        "filter_outliers_dict": {
            "filter_outliers": true,
            "iterations": 1,
            "std_devs": 2
        },
        "fit": "linear",
        "value": 0.010876665083500022
    },
    "Ar37": {
        "error": 0.0035969100281084913,
        "error_type": "SEM",
        "filter_outliers_dict": {
            "filter_outliers": true,
            "iterations": 1,
            "std_devs": 2
        },
        "fit": "linear",
        "value": -0.010832064205477287
    },
    "Ar38": {
        "error": 0.002710464017169335,
        "error_type": "SEM",
        "filter_outliers_dict": {
            "filter_outliers": true,
            "iterations": 1,
            "std_devs": 2
        },
        "fit": "linear",
        "value": 0.08236819207240983
    },
    "Ar39": {
        "error": 0.012374904970639871,
        "error_type": "SEM",
        "filter_outliers_dict": {
            "filter_outliers": true,
            "iterations": 1,
            "std_devs": 2
        },
        "fit": "parabolic",
        "value": 1.9005430486753185
    },
    "Ar40": {
        "error": 0.012133597829476048,
        "error_type": "SEM",
        "filter_outliers_dict": {
            "filter_outliers": true,
            "iterations": 1,
            "std_devs": 3
        },
        "fit": "parabolic",
        "value": 6.532485815010933
    },
    "Ar41": {
        "error": 0.01629093569467632,
        "error_type": "SEM",
        "filter_outliers_dict": {
            "filter_outliers": true,
            "iterations": 1,
            "std_devs": 3
        },
        "fit": "average",
        "value": -0.19169107011144004
    }
}