{
    "Ar36": {
        "error": 0.00024474630392648186,
        "error_type": "SEM",
        "filter_outliers_dict": {
            "filter_outliers": true,
            "iterations": 1,
            "std_devs": 3,
            "use_iqr_filtering": false,
            "use_standard_deviation_filtering": false
        },
        "fit": "linear",
        "fn": 279,
        "include_baseline_error": true,
        "n": 280,
        "outlier_excluded": [
            261
        ],
        "reviewed": true,
        "user_excluded": [],
        "value": 0.01755498434812148
    },
    "Ar37": {
        "error": 0.0036102352381774923,
        "error_type": "SEM",
        "filter_outliers_dict": {
            "filter_outliers": true,
            "iterations": 1,
            "std_devs": 3,
            "use_iqr_filtering": false,
            "use_standard_deviation_filtering": false
        },
        "fit": "linear",
        "fn": 280,
        "include_baseline_error": true,
        "n": 280,
        "outlier_excluded": [],
        "reviewed": true,
        "user_excluded": [],
        "value": 0.005784562298677078
    },
    "Ar38": {
        "error": 0.0034128172302560155,
        "error_type": "SEM",
        "filter_outliers_dict": {
            "filter_outliers": true,
            "iterations": 1,
            "std_devs": 3,
            "use_iqr_filtering": false,
            "use_standard_deviation_filtering": false
        },
        "fit": "linear",
        "fn": 279,
        "include_baseline_error": true,
        "n": 280,
        "outlier_excluded": [
            57
        ],
        "reviewed": true,
        "user_excluded": [],
        "value": 0.18076617595058836
    },
    "Ar39": {
        "error": 0.015654718294594,
        "error_type": "SEM",
        "filter_outliers_dict": {
            "filter_outliers": true,
            "iterations": 1,
            "std_devs": 3,
            "use_iqr_filtering": false,
            "use_standard_deviation_filtering": false
        },
        "fit": "parabolic",
        "fn": 277,
        "include_baseline_error": true,
        "n": 280,
        "outlier_excluded": [
            209,
            107,
            235
        ],
        "reviewed": true,
        "user_excluded": [],
        "value": 9.471222737075351
    },
    "Ar40": {
        "error": 0.008929642462342591,
        "error_type": "SEM",
        "filter_outliers_dict": {
            "filter_outliers": true,
            "iterations": 1,
            "std_devs": 3,
            "use_iqr_filtering": false,
            "use_standard_deviation_filtering": false
        },
        "fit": "linear",
        "fn": 280,
        "include_baseline_error": true,
        "n": 280,
        "outlier_excluded": [],
        "reviewed": true,
        "user_excluded": [],
        "value": 26.089547624775356
    },
    "Ar41": {
        "error": 0.018797115999631644,
        "error_type": "SEM",
        "filter_outliers_dict": {
            "filter_outliers": true,
            "iterations": 1,
            "std_devs": 3
        },
        "fit": "average",
        "value": -0.19129604576527873
    }
}