{
    "Ar36": {
        "error": 0.00021257741079906215,
        "error_type": "SEM",
        "filter_outliers_dict": {
            "filter_outliers": true,
            "iterations": 1,
            "std_devs": 3,
            "use_iqr_filtering": false,
            "use_standard_deviation_filtering": false
        },
        "fit": "linear",
        "fn": 278,
        "include_baseline_error": true,
        "n": 280,
        "outlier_excluded": [
            161,
            275
        ],
        "reviewed": true,
        "user_excluded": [],
        "value": 0.011319803128266054
    },
    "Ar37": {
        "error": 0.003342890406704232,
        "error_type": "SEM",
        "filter_outliers_dict": {
            "filter_outliers": true,
            "iterations": 1,
            "std_devs": 3,
            "use_iqr_filtering": false,
            "use_standard_deviation_filtering": false
        },
        "fit": "linear",
        "fn": 278,
        "include_baseline_error": true,
        "n": 280,
        "outlier_excluded": [
            176,
            95
        ],
        "reviewed": true,
        "user_excluded": [],
        "value": -0.01587396044849895
    },
    "Ar38": {
        "error": 0.0035334875055798667,
        "error_type": "SEM",
        "filter_outliers_dict": {
            "filter_outliers": true,
            "iterations": 1,
            "std_devs": 3,
            "use_iqr_filtering": false,
            "use_standard_deviation_filtering": false
        },
        "fit": "linear",
        "fn": 279,
        "include_baseline_error": true,
        "n": 280,
        "outlier_excluded": [
            167
        ],
        "reviewed": true,
        "user_excluded": [],
        "value": 0.0711525057983717
    },
    "Ar39": {
        "error": 0.014716012804003784,
        "error_type": "SEM",
        "filter_outliers_dict": {
            "filter_outliers": true,
            "iterations": 1,
            "std_devs": 3,
            "use_iqr_filtering": false,
            "use_standard_deviation_filtering": false
        },
        "fit": "parabolic",
        "fn": 279,
        "include_baseline_error": true,
        "n": 280,
        "outlier_excluded": [
            27
        ],
        "reviewed": true,
        "user_excluded": [],
        "value": 1.2187686246087488
    },
    "Ar40": {
        "error": 0.012549033898651545,
        "error_type": "SEM",
        "filter_outliers_dict": {
            "filter_outliers": true,
            "iterations": 1,
            "std_devs": 3,
            "use_iqr_filtering": false,
            "use_standard_deviation_filtering": false
        },
        "fit": "parabolic",
        "fn": 279,
        "include_baseline_error": true,
        "n": 280,
        "outlier_excluded": [
            191
        ],
        "reviewed": true,
        "user_excluded": [],
        "value": 4.97692954312683
    },
    "Ar41": {
        "error": 0.0177329841133689,
        "error_type": "SEM",
        "filter_outliers_dict": {
            "filter_outliers": true,
            "iterations": 1,
            "std_devs": 3
        },
        "fit": "average",
        "value": -0.1742632910763801
    }
}